cq_server/__init__.py
cq_server/cli.py
cq_server/exporter.py
cq_server/module_manager.py
cq_server/server.py
cq_server/static/images/icon_cq.png
cq_server/static/vendor/three-cad-viewer.css
cq_server/static/vendor/three-cad-viewer.js
cq_server/static/viewer.css
cq_server/static/viewer.js
cq_server/templates/viewer.html
cq_server/ui.py
cadquery_server-0.4.1.dist-info/entry_points.txt
cadquery_server-0.4.1.dist-info/LICENSE
cadquery_server-0.4.1.dist-info/WHEEL
cadquery_server-0.4.1.dist-info/METADATA
cadquery_server-0.4.1.dist-info/RECORD
