Metadata-Version: 2.1
Name: cadquery-server
Version: 0.4.1
Summary: A web server used to render 3d models from CadQuery code, and eventually build a static website as a showcase for your projects.
Home-page: https://github.com/roipoussiere/cadquery-server
License: MIT
Keywords: cad,cadquery,3d,parametric,modeling
Author: Roipoussiere
Requires-Python: >=3.8,<3.11
Classifier: Framework :: Flask
Classifier: License :: OSI Approved :: MIT License
Classifier: Programming Language :: Python :: 3
Classifier: Programming Language :: Python :: 3.8
Classifier: Programming Language :: Python :: 3.9
Classifier: Programming Language :: Python :: 3.10
Classifier: Topic :: Multimedia :: Graphics :: 3D Modeling
Provides-Extra: cadquery
Requires-Dist: CairoSVG (>=2.5.2,<3.0.0)
Requires-Dist: Flask (>=2.2.2,<3.0.0)
Requires-Dist: cadquery (==2.2.0b0); extra == "cadquery"
Requires-Dist: cadquery-massembly (>=0.9.0,<0.10.0)
Requires-Dist: casadi (>=3.5.6rc2,<4.0.0); extra == "cadquery"
Requires-Dist: jupyter-cadquery (>=3.2.2,<4.0.0)
Requires-Dist: matplotlib (>=3.5.3,<4.0.0)
Requires-Dist: minify-html (>=0.10.0,<0.11.0)
Project-URL: Repository, https://github.com/roipoussiere/cadquery-server
